pytest_offline/__init__.py
pytest_offline/exceptions.py
pytest_offline/plugin.py
pytest_offline/utils.py
pytest_offline-0.1.0.dist-info/LICENSE
pytest_offline-0.1.0.dist-info/METADATA
pytest_offline-0.1.0.dist-info/WHEEL
pytest_offline-0.1.0.dist-info/entry_points.txt
pytest_offline-0.1.0.dist-info/RECORD
